[
{"name":"易", "comp":"日勿⼃"},
{"name":"黄", "comp":"龷由"},
{"name":"复", "comp":"𠂉日⼃"},
{"name":"送", "comp":"䒑大⼂"},
{"name":"团", "comp":"囗才⼀"},
{"name":"句", "comp":"勹口⼁"},
{"name":"官", "comp":"宀㠯⼁"},
{"name":"敢", "comp":"乛耳⼃"},
{"name":"修", "comp":"夂"},
{"name":"照", "comp":"日刀"},
{"name":"丽", "comp":"丽⼀"},
{"name":"备", "comp":"夂田⼁"},
{"name":"急", "comp":"刍心⼂"},
{"name":"忙", "comp":"忄亡"},
{"name":"母", "comp":"母⺂"},
{"name":"欢", "comp":"又欠⼃"},
{"name":"英", "comp":"艹冂⼀"},
{"name":"古", "comp":"古⼀⼁"},
{"name":"底", "comp":"广氏⼂"},
{"name":"巴", "comp":"巴⺂⼁"},
{"name":"帮", "comp":"阝"},
{"name":"终", "comp":"纟夂⼂"},
{"name":"势", "comp":"执力"},
{"name":"娘", "comp":"女丶"},
{"name":"热", "comp":"执灬⼂"},
{"name":"显", "comp":"日业⼁"},
{"name":"朝", "comp":"𠦝月⼃"},
{"name":"错", "comp":"钅龷"},
{"name":"持", "comp":"扌土⼀⼁"},
{"name":"调", "comp":"讠冂"},
{"name":"宝", "comp":"宀王⼂"},
{"name":"香", "comp":"禾日⼁"},
{"name":"低", "comp":"亻氏"},
{"name":"丝", "comp":""},
{"name":"曾", "comp":"曾⼂⼃"},
{"name":"冲", "comp":"冫中⼁"},
{"name":"线", "comp":"纟戋⼀"},
{"name":"级", "comp":"纟及"},
{"name":"示", "comp":"示⼀⼀"},
{"name":"改", "comp":"己攵⼃"},
{"name":"待", "comp":"彳土⼀⼁"},
{"name":"包", "comp":"勹巳⺂"},
{"name":"台", "comp":"厶口⼁"},
{"name":"沉", "comp":"氵冖⼃"},
{"name":"愿", "comp":"厂白⼁"},
{"name":"久", "comp":"久⼃⺂"},
{"name":"希", "comp":"乂𠂇⼁"},
{"name":"木", "comp":"木⼀⼁⼃"},
{"name":"响", "comp":"口⼁"},
{"name":"破", "comp":"石皮"},
{"name":"首", "comp":"䒑自⼃"},
{"name":"模", "comp":"木莫⼀"},
{"name":"脚", "comp":"月去⺂⼁"},
{"name":"害", "comp":"宀丰⼁"},
{"name":"约", "comp":"纟勹⼂"},
{"name":"资", "comp":"次贝⼁"},
{"name":"穿", "comp":"穴牙"},
{"name":"联", "comp":"耳䒑"},
{"name":"哈", "comp":"口合"},
{"name":"树", "comp":"木又"},
{"name":"雪", "comp":"⻗彐⺂"},
{"name":"楚", "comp":"林疋"},
{"name":"注", "comp":"氵主"},
{"name":"引", "comp":"弓丨⼁"},
{"name":"护", "comp":"扌户"},
{"name":"另", "comp":"口力⺂"},
{"name":"故", "comp":"古攵⼃"},
{"name":"村", "comp":"木寸⼀"},
{"name":"存", "comp":"子⺂"},
{"name":"嘴", "comp":"口此⼃"},
{"name":"依", "comp":"亻衣⼂"},
{"name":"诉", "comp":"讠斤"},
{"name":"造", "comp":"告辶⼂"},
{"name":"技", "comp":"扌十"},
{"name":"露", "comp":"⻗⻊"},
{"name":"除", "comp":"阝亼"},
{"name":"慢", "comp":"忄日⼁"},
{"name":"具", "comp":"八"},
{"name":"摇", "comp":"扌爫"},
{"name":"观", "comp":"又见⼁"},
{"name":"楼", "comp":"木米"},
{"name":"商", "comp":"冂⼃"},
{"name":"型", "comp":"开刂⼀"},
{"name":"府", "comp":"广亻⼀"},
{"name":"停", "comp":"亻⼀"},
{"name":"爷", "comp":"父卩⺂"},
{"name":"铁", "comp":"钅丿⼀"},
{"name":"段", "comp":"段⼃⼁"},
{"name":"广", "comp":"广⼂⼀"},
{"name":"念", "comp":"今心⼂"},
{"name":"组", "comp":"纟且⼁"},
{"name":"节", "comp":"艹卩⺂"},
{"name":"需", "comp":"⻗而"},
{"name":"议", "comp":"讠义⼂"},
{"name":"举", "comp":"八⼀"},
{"name":"支", "comp":"十又⺂"},
{"name":"细", "comp":"纟田"},
{"name":"跑", "comp":"⻊勹⺂"},
{"name":"维", "comp":"纟隹"},
{"name":"异", "comp":"巳廾⼀"},
{"name":"陈", "comp":"阝⼁"},
{"name":"乱", "comp":"舌乚"},
{"name":"况", "comp":"冫口⼃"},
{"name":"忽", "comp":"勿心⼂⺂"},
{"name":"妈", "comp":"女马"},
{"name":"刀", "comp":"刀⺂⼃"},
{"name":"痛", "comp":"疒甬⺂"},
{"name":"群", "comp":"尹口⼂"},
{"name":"居", "comp":"尸古"},
{"name":"速", "comp":"束辶"},
{"name":"兄", "comp":"口儿"},
{"name":"睛", "comp":"目青⼀"},
{"name":"究", "comp":"穴九⼃"},
{"name":"斗", "comp":"⺀十⼀⼁"},
{"name":"卡", "comp":"上卜⼁"},
{"name":"甚", "comp":"其乚⺂"},
{"name":"帝", "comp":"巾"},
{"name":"喝", "comp":"口日⼃"},
{"name":"态", "comp":"大丶⼂"},
{"name":"怀", "comp":"忄不⼀"},
{"name":"局", "comp":"尸𠃌"},
{"name":"派", "comp":"氵⺁"},
{"name":"杨", "comp":"木㇡⼃"},
{"name":"谢", "comp":"讠身"},
{"name":"脑", "comp":"月㐫⼂"},
{"name":"病", "comp":"疒𰀃⼃"},
{"name":"顿", "comp":"屯页⼀"},
{"name":"治", "comp":"氵厶⼁"},
{"name":"福", "comp":"礻𠮛⼁"},
{"name":"角", "comp":"角⼃⺂"},
{"name":"旁", "comp":"方"},
{"name":"威", "comp":"戊一⺂"},
{"name":"叶", "comp":"口十"},
{"name":"京", "comp":"京⼂⼀"},
{"name":"围", "comp":"囗韦⼀"},
{"name":"园", "comp":"囗元⼀⼀"},
{"name":"皮", "comp":"皮⺂"},
{"name":"雨", "comp":"雨⼀⼁⺂"},
{"name":"号", "comp":"口丂⼀"},
{"name":"密", "comp":"宀心⼃"},
{"name":"须", "comp":"彡页⼀"},
{"name":"推", "comp":"扌隹"},
{"name":"背", "comp":"北⺝⼁"},
{"name":"河", "comp":"氵可⼀"},
{"name":"亮", "comp":"几⼃"},
{"name":"姑", "comp":"女古"},
{"name":"证", "comp":"讠正⼀"},
{"name":"费", "comp":"弓⼁"},
{"name":"汉", "comp":"氵又⺂"},
{"name":"志", "comp":"士心⼂"},
{"name":"查", "comp":"木旦⼁"},
{"name":"圣", "comp":"又土⼀⼁⼀"},
{"name":"呼", "comp":"口乎⼃"},
{"name":"讲", "comp":"讠井⼀"},
{"name":"续", "comp":"纟十⺂"},
{"name":"标", "comp":"木示⼀"},
{"name":"共", "comp":"共⼀⼁⼁"},
{"name":"尼", "comp":"尸匕⼃"},
{"name":"米", "comp":"米⼂⼃"},
{"name":"际", "comp":"阝示⼀"},
{"name":"招", "comp":"扌刀⼁"},
{"name":"超", "comp":"走刀⼁"},
{"name":"差", "comp":"⺶工⼀⼁"},
{"name":"仍", "comp":"亻乃⺂"},
{"name":"块", "comp":"土⼃"},
{"name":"莫", "comp":"莫⼀⼁"},
{"name":"游", "comp":"氵𭤨⺂"},
{"name":"药", "comp":"艹纟"},
{"name":"船", "comp":"舟几⼁"},
{"name":"网", "comp":"冂乂⼃"},
{"name":"掌", "comp":"手⼃⼀"},
{"name":"呀", "comp":"口牙⼀"},
{"name":"掉", "comp":"扌⺊⼁"},
{"name":"皇", "comp":"白王⼀"},
{"name":"玩", "comp":"王元⼀"},
{"name":"梦", "comp":"林夕⼃"},
{"name":"选", "comp":"先辶"},
{"name":"争", "comp":"争⼃⺂"},
{"name":"疑", "comp":"匕矢⺂"},
{"name":"既", "comp":"旡⼀"},
{"name":"波", "comp":"氵皮"},
{"name":"闪", "comp":"门人⼃"},
{"name":"室", "comp":"宀至"},
{"name":"料", "comp":"米⺀"},
{"name":"简", "comp":"⺮门⼁"},
{"name":"佛", "comp":"亻弓⼃"},
{"name":"堂", "comp":"土⼀"},
{"name":"索", "comp":"糸"},
{"name":"规", "comp":"夫见⼁"},
{"name":"朋", "comp":"月月⼃"},
{"name":"攻", "comp":"工攵"},
{"name":"章", "comp":"音十"},
{"name":"礼", "comp":"礻乚⺂"},
{"name":"鬼", "comp":"鬼⼃⼁"},
{"name":"春", "comp":"𡗗日⼁"},
{"name":"刘", "comp":"文刂⼁"},
{"name":"严", "comp":"亚丿⼃"},
{"name":"赶", "comp":"走干⼀"},
{"name":"睡", "comp":"目垂"},
{"name":"屋", "comp":"尸至"},
{"name":"食", "comp":"食⼃"},
{"name":"饭", "comp":"饣⺁⺂"},
{"name":"济", "comp":"氵文⼃"},
{"name":"试", "comp":"讠弋⼀⼁"},
{"name":"仙", "comp":"亻山⼁"},
{"name":"导", "comp":"巳寸"},
{"name":"参", "comp":"彡⼃"},
{"name":"沙", "comp":"氵少⼁"},
{"name":"永", "comp":"丶㇉⺂"},
{"name":"肯", "comp":"止⺝⼁"},
{"name":"环", "comp":"王不⼀⼃"},
{"name":"农", "comp":"农⼂⺂"},
{"name":"恶", "comp":"亚心⼂"},
{"name":"称", "comp":"禾尔"},
{"name":"止", "comp":"止⼁⼀"},
{"name":"初", "comp":"衤刀⺂"},
{"name":"医", "comp":"匚矢⼃"},
{"name":"敌", "comp":"舌攵⼃⼀"},
{"name":"跳", "comp":"⻊儿"},
{"name":"假", "comp":"亻叚⺂"},
{"name":"左", "comp":"𠂇工⼀⼁"},
{"name":"散", "comp":"龷⺝"},
{"name":"温", "comp":"氵日⼁"},
{"name":"继", "comp":"纟米"},
{"name":"换", "comp":"扌⺈⼁"},
{"name":"权", "comp":"木又⺂"},
{"name":"银", "comp":"钅艮⺂"},
{"name":"君", "comp":"尹口⼁⺂"},
{"name":"退", "comp":"艮辶⼂"},
{"name":"闻", "comp":"门耳⼀"},
{"name":"激", "comp":"氵白⼂"},
{"name":"画", "comp":"一田⺂"},
{"name":"较", "comp":"车六⼃"},
{"name":"烈", "comp":"歹刂⼂"},
{"name":"独", "comp":"犭虫"},
{"name":"球", "comp":"王求"},
{"name":"土", "comp":"土⼀⼁⼀⼀"},
{"name":"层", "comp":"尸云"},
{"name":"卫", "comp":"卩一⼀"},
{"name":"抱", "comp":"扌勹⺂"},
{"name":"草", "comp":"艹日⼀"},
{"name":"专", "comp":"二㇉"},
{"name":"烟", "comp":"火因"},
{"name":"余", "comp":"亼朩"},
{"name":"秋", "comp":"禾火⼂"},
{"name":"顺", "comp":"川页⼀⼃"},
{"name":"顾", "comp":"厂⺋"},
{"name":"否", "comp":"不口⼁"},
{"name":"值", "comp":"亻直⼀"},
{"name":"考", "comp":"耂与⼀"},
{"name":"冰", "comp":"冫水⼁"},
{"name":"境", "comp":"土音"},
{"name":"妹", "comp":"女未⼀"},
{"name":"恐", "comp":"工几"},
{"name":"怒", "comp":"奴心⼂"},
{"name":"伯", "comp":"亻白⼃⼁"},
{"name":"质", "comp":"⺁十"},
{"name":"艺", "comp":"艹乙⺂"},
{"name":"味", "comp":"口未⼀"},
{"name":"历", "comp":"厂力"},
{"name":"构", "comp":"木勹⺂"},
{"name":"研", "comp":"石开⼀"},
{"name":"施", "comp":"𭤨也⺂"},
{"name":"贵", "comp":"𠀐贝⼁"},
{"name":"委", "comp":"禾女"},
{"name":"渐", "comp":"氵车"},
{"name":"淡", "comp":"氵火⼂"},
{"name":"史", "comp":"口乂⼃"},
{"name":"校", "comp":"木六⼃"},
{"name":"狂", "comp":"犭王⼀"},
{"name":"馆", "comp":"饣宀"},
{"name":"板", "comp":"木⺁⺂"},
{"name":"排", "comp":"扌非⼁"},
{"name":"价", "comp":"亻人⼃⼁⼁"},
{"name":"街", "comp":"彳圭⼀"},
{"name":"宫", "comp":"宀口⼁"},
{"name":"追", "comp":"丿㠯⼂"},
{"name":"靠", "comp":"告非⼁"},
{"name":"忍", "comp":"刀丶⼂⺂"},
{"name":"普", "comp":"䒑业⼁"},
{"name":"致", "comp":"至攵⼃⼀"},
{"name":"钟", "comp":"钅中⼁"},
{"name":"娜", "comp":"女𭃂⺂"},
{"name":"耳", "comp":"耳⼀⼁⼁"},
{"name":"属", "comp":"尸丿"},
{"name":"忘", "comp":"亡心⼂⺂"},
{"name":"苏", "comp":"艹力⼂"},
{"name":"伙", "comp":"亻火⼂"},
{"name":"仅", "comp":"亻又⺂"},
{"name":"景", "comp":"日京⼂"},
{"name":"松", "comp":"木公"},
{"name":"州", "comp":"川⼂"},
{"name":"胡", "comp":"古月⼃"},
{"name":"纪", "comp":"纟己⺂"},
{"name":"印", "comp":"一"},
{"name":"赵", "comp":"走乂"},
{"name":"置", "comp":"罒直⼀"},
{"name":"投", "comp":"扌殳⼃"},
{"name":"列", "comp":"歹刂⼁"},
{"name":"隐", "comp":"阝刍"},
{"name":"缓", "comp":"纟爫⼀"},
{"name":"座", "comp":"广从⼀"},
{"name":"庄", "comp":"广土⼀"},
{"name":"幸", "comp":"土𢆉⼂"},
{"name":"副", "comp":"𠮛田"},
{"name":"充", "comp":"儿⼃"},
{"name":"守", "comp":"宀寸⼀⼁"},
{"name":"胜", "comp":"月生⼃"},
{"name":"救", "comp":"求攵⼃"},
{"name":"射", "comp":"身寸⼀"},
{"name":"齐", "comp":"文⼃⼁"},
{"name":"顶", "comp":"丁页⼀"},
{"name":"助", "comp":"且力"},
{"name":"右", "comp":"𠂇口⼁"},
{"name":"素", "comp":"龶糸⺂"},
{"name":"唐", "comp":"广肀"},
{"name":"抓", "comp":"扌爪⼃"},
{"name":"巨", "comp":"匚⺂"},
{"name":"毛", "comp":"毛⼃⼀"},
{"name":"诗", "comp":"讠土⼀⼁"},
{"name":"弄", "comp":"王廾⼀⼃"},
{"name":"防", "comp":"阝方"},
{"name":"雅", "comp":"牙隹⼃"},
{"name":"源", "comp":"氵厂⼃"},
{"name":"户", "comp":"户⼂⺂"},
{"name":"湖", "comp":"氵古⼃"},
{"name":"项", "comp":"工页⼀"},
{"name":"党", "comp":"儿"},
{"name":"压", "comp":"厂土⼂"},
{"name":"寒", "comp":"𡨄⺀⼂"},
{"name":"效", "comp":"六乂⼃"},
{"name":"奥", "comp":"米"},
{"name":"毫", "comp":"毛⼃"},
{"name":"增", "comp":"土曾⼂"},
{"name":"险", "comp":"阝亼⼂"},
{"name":"状", "comp":"丬犬⼀"},
{"name":"按", "comp":"扌宀"},
{"name":"买", "comp":"乛⺀⼀"},
{"name":"禁", "comp":"林示⼀"},
{"name":"阴", "comp":"阝月"},
{"name":"叹", "comp":"口又⺂"},
{"name":"蓝", "comp":"艹𰀢⼁"},
{"name":"察", "comp":"宀⼀"},
{"name":"承", "comp":"了三⺂"},
{"name":"省", "comp":"少目"},
{"name":"份", "comp":"亻分⼃⼂"},
{"name":"托", "comp":"扌丿⼀"},
{"name":"恩", "comp":"因心⼂⺂"},
{"name":"责", "comp":"龶贝⼁"},
{"name":"挥", "comp":"扌冖⼀"},
{"name":"洛", "comp":"氵各⼃"},
{"name":"妇", "comp":"女彐⺂"},
{"name":"牛", "comp":"牛⼃⼀"},
{"name":"习", "comp":"习⺂"},
{"name":"警", "comp":"𬜠口⼃"},
{"name":"默", "comp":"黑犬⼀"},
{"name":"岁", "comp":"山夕"},
{"name":"骑", "comp":"马大⼀"},
{"name":"股", "comp":"月殳⼃"},
{"name":"划", "comp":"戈刂⼁"},
{"name":"负", "comp":"⺈贝⼁"},
{"name":"枪", "comp":"木人"},
{"name":"梅", "comp":"木𠂉"},
{"name":"采", "comp":"爫木⼀"},
{"name":"吸", "comp":"口及⼃"},
{"name":"富", "comp":"宀𠮛⼁"},
{"name":"舞", "comp":"𠂉卌"},
{"name":"肉", "comp":"内人⼃"},
{"name":"镇", "comp":"钅直⼃⼂"},
{"name":"野", "comp":"里予⺂"},
{"name":"床", "comp":"广木⼀"},
{"name":"某", "comp":"甘木"},
{"name":"醒", "comp":"酉日⼃"},
{"name":"验", "comp":"马亼"},
{"name":"读", "comp":"讠十⺂"},
{"name":"担", "comp":"扌旦⼁"},
{"name":"毒", "comp":"龶母"},
{"name":"封", "comp":"圭寸"},
{"name":"尚", "comp":"⺌冂"},
{"name":"纳", "comp":"纟内⼁"},
{"name":"伊", "comp":"亻尹⺂"},
{"name":"营", "comp":"𫇦口⼁"},
{"name":"猛", "comp":"犭子⼁"},
{"name":"短", "comp":"矢豆⼀"},
{"name":"旧", "comp":"丨日⼁"},
{"name":"脱", "comp":"月𠮦⼃"},
{"name":"遇", "comp":"日⽱⼂⺂"},
{"name":"词", "comp":"讠𠃌"},
{"name":"坏", "comp":"土不"},
{"name":"控", "comp":"扌穴⼀"},
{"name":"田", "comp":"田⼁⺂"},
{"name":"乡", "comp":"丿⼃"},
{"name":"刺", "comp":"朿刂⼁"},
{"name":"啦", "comp":"口扌⼂"},
{"name":"孙", "comp":"孑小"},
{"name":"翻", "comp":"釆田⺂"},
{"name":"藏", "comp":"艹戊⺂"},
{"name":"虎", "comp":"虍几⼃"},
{"name":"坚", "comp":"𰀡土⼀"},
{"name":"良", "comp":"丶艮⺂"},
{"name":"柔", "comp":"矛木⼀⼁⼃"},
{"name":"眉", "comp":"𠃜目⼁"},
{"name":"伸", "comp":"亻日⼁⼁"},
{"name":"窗", "comp":"穴⼃"},
{"name":"咱", "comp":"口自⼃"},
{"name":"婚", "comp":"女氏⼁"},
{"name":"戏", "comp":"又戈⼀"},
{"name":"逃", "comp":"儿⼂⺂"},
{"name":"赛", "comp":"𡨄贝⼁⺂"},
{"name":"扬", "comp":"扌㇡⼃"},
{"name":"凡", "comp":"几丶⼂"},
{"name":"凌", "comp":"冫土⼃"},
{"name":"配", "comp":"酉己"},
{"name":"练", "comp":"纟⺂"},
{"name":"率", "comp":"亠幺⼂"},
{"name":"贝", "comp":"贝⼁"},
{"name":"宇", "comp":"宀于"},
{"name":"茶", "comp":"艹人⼀"},
{"name":"优", "comp":"亻尢⼂"},
{"name":"杰", "comp":"木灬⼂"},
{"name":"吉", "comp":"吉⼀⼁"},
{"name":"卷", "comp":"龹⺋⺂"},
{"name":"创", "comp":"人⺋⼁"},
{"name":"罢", "comp":"罒去⼀"},
{"name":"秀", "comp":"禾乃⺂"},
{"name":"归", "comp":"彐⺂"},
{"name":"哭", "comp":"吅犬⼀"},
{"name":"凤", "comp":"几又⺂"},
{"name":"陆", "comp":"阝𰀁"},
{"name":"端", "comp":"立山⼀"},
{"name":"休", "comp":"亻木⼀"},
{"name":"库", "comp":"广车⼀"},
{"name":"序", "comp":"广予⺂"},
{"name":"善", "comp":"羊䒑⼁"},
{"name":"秘", "comp":"禾心⼃"},
{"name":"拍", "comp":"扌白⼃⼁"},
{"name":"案", "comp":"宀女⼀"},
{"name":"迷", "comp":"米辶⼂"},
{"name":"震", "comp":"⻗辰⼀"},
{"name":"免", "comp":""},
{"name":"职", "comp":"耳口"},
{"name":"洋", "comp":"氵羊⼂"},
{"name":"寻", "comp":"彐寸⼀"},
{"name":"养", "comp":"羊丶⼃⼁"},
{"name":"珠", "comp":"王丿⼀"},
{"name":"歌", "comp":"可可⼃"},
{"name":"盘", "comp":"舟皿⼁"},
{"name":"朱", "comp":"丿未⼀"},
{"name":"演", "comp":"氵宀⼀"},
{"name":"虚", "comp":"虍业⼁"},
{"name":"呆", "comp":"呆⼁⺂"},
{"name":"付", "comp":"亻寸⼀"},
{"name":"笔", "comp":"⺮毛⼃"},
{"name":"适", "comp":"舌辶⼂"},
{"name":"康", "comp":"广⺕"},
{"name":"麻", "comp":"麻⼂⼀"},
{"name":"宁", "comp":"宀丁⼀"},
{"name":"吴", "comp":"口天⼀"},
{"name":"欲", "comp":"八人⼁"},
{"name":"罪", "comp":"罒非"},
{"name":"恨", "comp":"忄艮⺂"},
{"name":"杂", "comp":"九朩⼀"},
{"name":"套", "comp":"大镸⼀"},
{"name":"骨", "comp":"骨⼁"},
{"name":"紫", "comp":"此糸⺂"},
{"name":"软", "comp":"车欠⼃"},
{"name":"蒙", "comp":"𫇦一⼀⼃"},
{"name":"弹", "comp":"弓单⼂"},
{"name":"育", "comp":"⺝⼁"},
{"name":"企", "comp":"人止⼁"},
{"name":"仿", "comp":"亻方⼂"},
{"name":"泪", "comp":"氵目⼁"},
{"name":"曲", "comp":"曲⼁⺂"},
{"name":"鱼", "comp":"鱼⼃⺂"},
{"name":"兽", "comp":"丷田⼀"},
{"name":"略", "comp":"田各⼃"},
{"name":"握", "comp":"扌尸⼀"},
{"name":"厅", "comp":"厂丁⼀"},
{"name":"厉", "comp":"厂万⼀"},
{"name":"卖", "comp":"十乛"},
{"name":"供", "comp":"亻共⼀"},
{"name":"丹", "comp":"冂亠"},
{"name":"喊", "comp":"口戊⼀⼁"},
{"name":"峰", "comp":"山夂"},
{"name":"灯", "comp":"火丁⼀"},
{"name":"绿", "comp":"纟彐⼁"},
{"name":"夏", "comp":"丆目"},
{"name":"塔", "comp":"土艹⼃⼂"},
{"name":"桌", "comp":"⺊日⼀"},
{"name":"范", "comp":"落⺋⺂"},
{"name":"限", "comp":"阝艮⺂"},
{"name":"县", "comp":"且厶"},
{"name":"讨", "comp":"讠寸⼀⼁"},
{"name":"革", "comp":"革⼀"},
{"name":"燕", "comp":"廿口⼁⼀"},
{"name":"欧", "comp":"区欠⼃"},
{"name":"临", "comp":"𠂉⼂"},
{"name":"移", "comp":"禾夕⼃"},
{"name":"洞", "comp":"氵冂⼀"},
{"name":"剧", "comp":"尸古⼁"}]